.gitignore
.travis.yml
LICENSE
README.md
generate_dataset.py
requirements.txt
setup.py
setup_env.ini
setup_foregrounds.ini
setup_instrument.ini
setup_scanning.ini
LaFabrique/InputScan.py
LaFabrique/__init__.py
LaFabrique/communication.py
LaFabrique/covariance.py
LaFabrique/foreground.py
LaFabrique/noise.py
LaFabrique/scanning_strategy.py
LaFabrique/util_CMB.py
LaFabrique.egg-info/PKG-INFO
LaFabrique.egg-info/SOURCES.txt
LaFabrique.egg-info/dependency_links.txt
LaFabrique.egg-info/requires.txt
LaFabrique.egg-info/top_level.txt
additional_files/outputs.png
additional_files/perf_100MC_nside2048.png
additional_files/perf_1MC_nside2048.png
test/check_maps.py
test/setup_env_test.ini
test/setup_instrument_test.ini
test/setup_scanning_test.ini
test/test_cholesky.py
test/test_cov.py
test/test_healpy.py
test/benchmark/masks/IQU_nside64_test_weights_freq150_HF.fits
test/benchmark/masks/IQU_nside64_test_weights_freq150_MF.fits
test/benchmark/masks/IQU_nside64_test_weights_freq220_HF.fits
test/benchmark/masks/IQU_nside64_test_weights_freq220_UHF.fits
test/benchmark/masks/IQU_nside64_test_weights_freq270_UHF.fits
test/benchmark/masks/IQU_nside64_test_weights_freq27_LF.fits
test/benchmark/masks/IQU_nside64_test_weights_freq39_LF.fits
test/benchmark/masks/IQU_nside64_test_weights_freq90_MF.fits
test/benchmark/masks/setup_scanning.ini
test/benchmark/masks/test.hdf5
test/benchmark/noise/IQU_nside64_test_freq150_HF_white_noise_sim000.fits
test/benchmark/noise/IQU_nside64_test_freq150_MF_white_noise_sim000.fits
test/benchmark/noise/IQU_nside64_test_freq220_HF_white_noise_sim000.fits
test/benchmark/noise/IQU_nside64_test_freq220_UHF_white_noise_sim000.fits
test/benchmark/noise/IQU_nside64_test_freq270_UHF_white_noise_sim000.fits
test/benchmark/noise/IQU_nside64_test_freq27_LF_white_noise_sim000.fits
test/benchmark/noise/IQU_nside64_test_freq39_LF_white_noise_sim000.fits
test/benchmark/noise/IQU_nside64_test_freq90_MF_white_noise_sim000.fits
test/benchmark/noise/setup_instrument.ini