Metadata-Version: 1.1
Name: LaFabrique
Version: 0.1.11
Summary: Generate simulated datasets for CMB experiments
Home-page: https://github.com/JulienPeloton/LaFabrique
Author: Julien Peloton
Author-email: j.peloton@sussex.ac.uk
License: GPL-3.0
Download-URL: https://github.com/JulienPeloton/LaFabrique/archive/0.1.11.zip
Keywords: CMB,simulations,experiments
Platform: UNKNOWN
Classifier: Programming Language :: Python :: 2
Classifier: Programming Language :: Python :: 2.7
